oopdb/ColumnConfig.py
oopdb/Expression.py
oopdb/OOPDB.py
oopdb/Utils.py
oopdb/__init__.py
oopdb-0.0.5.dist-info/METADATA
oopdb-0.0.5.dist-info/WHEEL
oopdb-0.0.5.dist-info/top_level.txt
oopdb-0.0.5.dist-info/RECORD
