Metadata-Version: 2.1
Name: oopdb
Version: 0.0.5
Summary: OOP abstraction/wrapper for work with SQL data bases
Home-page: https://github.com/Basicula/OOPDB
Author: Basicula
Author-email: maksim.basum@gmail.com
License: UNKNOWN
Project-URL: Bug Tracker, https://github.com/Basicula/OOPDB/issues
Platform: UNKNOWN
Classifier: Programming Language :: Python :: 3
Classifier: Operating System :: OS Independent
